{
	"configurations" : 
	[
		{
			"directories" : 
			[
				{
					"build" : ".",
					"minimumCMakeVersion" : 
					{
						"string" : "3.20"
					},
					"projectIndex" : 0,
					"source" : ".",
					"targetIndexes" : 
					[
						0
					]
				}
			],
			"name" : "Debug",
			"projects" : 
			[
				{
					"directoryIndexes" : 
					[
						0
					],
					"name" : "CC",
					"targetIndexes" : 
					[
						0
					]
				}
			],
			"targets" : 
			[
				{
					"directoryIndex" : 0,
					"id" : "CC::@6890427a1f51a3e7e1df",
					"jsonFile" : "target-CC-Debug-d257676662c0b8b55852.json",
					"name" : "CC",
					"projectIndex" : 0
				}
			]
		}
	],
	"kind" : "codemodel",
	"paths" : 
	{
		"build" : "C:/Users/mrchl/STM32CubeIDE/workspace_1.12.1/CC/CC/build/debug/build",
		"source" : "C:/Users/mrchl/STM32CubeIDE/workspace_1.12.1/CC/CC"
	},
	"version" : 
	{
		"major" : 2,
		"minor" : 2
	}
}
